synthdef_parser/__init__.py
synthdef_parser/parser.py
synthdef_parser-0.1.0.dist-info/licenses/LICENSE
tests/__init__.py
tests/test_parser.py
synthdef_parser-0.1.0.dist-info/METADATA
synthdef_parser-0.1.0.dist-info/WHEEL
synthdef_parser-0.1.0.dist-info/top_level.txt
synthdef_parser-0.1.0.dist-info/RECORD
