Metadata-Version: 2.4
Name: synthdef-parser
Version: 0.1.0
Summary: A parser for SuperCollider SynthDef binary files
Author: rexmalebka
Author-email: rexmalebka <rexmalebka@krutt.org>
License-Expression: MIT
Project-URL: Homepage, https://github.com/rexmalebka/synthdef-parser
Requires-Python: >=3.7
License-File: LICENSE
Dynamic: author
Dynamic: license-file
Dynamic: requires-python
